{
  "title": " (주)퍼브 LMS 프로젝트 개발자·기획자 프리랜서 채용",
  "company": "㈜퍼브",
  "experience": "경력 (2년이상)",
  "education": "초대졸이상",
  "employmentType": "계약직 프리랜서",
  "salary": "회사내규에 따름 - 면접 후 결정",
  "location": "경기도 과천시 , 안양시 동안구 , 안양시 만안구 , 의왕시 , 경기전지역 , 서울전지역 지도",
  "workingHours": "-",
  "skills": "JAVA, Javascript, MySQL, Oracle, React, ReactJS, Spring, Spring Boot, 풀스택, Next.js",
  "industry": "솔루션·SI·CRM·ERP",
  "employees": "36명",
  "established": "2014년 (12년차)",
  "companyType": "벤처기업 (비상장)",
  "website": "firstbrain.co.kr",
  "coreCompetencies": "-",
  "preferredQualifications": "-",
  "position": "-",
  "certification": "강소기업",
  "revenue": "59억 5,093만원",
  "isImageType": false,
  "detailedTextElementExists": false,
  "detailedText": "EMPTY_TEXT",
  "imageUrl": ""
}