{
  "title": " [분당] 2년차 이상 JAVA 웹개발 -경력개발자 모집합니다:)",
  "company": "조앤소프트㈜",
  "experience": "경력 (2년이상)",
  "education": "초대졸이상",
  "employmentType": "정규직 수습기간협의",
  "salary": "회사내규에 따름 - 면접 후 결정",
  "location": "경기도 성남시 분당구 , 성남시 중원구 , 성남시 수정구 , 하남시 , 과천시 , 의왕시 , 서울시 송파구 , 강남구 , 서초구 지도",
  "workingHours": "-",
  "skills": "JAVA, JSP, MySQL, Websquare",
  "industry": "컴퓨터 프로그래밍 서비스업",
  "employees": "19명",
  "established": "2016년 (10년차)",
  "companyType": "중소기업 (비상장)",
  "website": "jonsoft.co.kr",
  "coreCompetencies": "성취지향성, 협동심, 성장지향성",
  "preferredQualifications": "기본우대 관련 학과 전공자 더보기 기본우대 관련 학과 전공자, 관련 자격증 보유자, 유관업무 경력자(4년) 우대조건 레이어 닫기",
  "position": "-",
  "certification": "-",
  "revenue": "14억 4,061만원",
  "isImageType": false,
  "detailedText": "EMPTY_TEXT1"
}